{
  "/v0/push/prefs": {
    "data": {
      "type": "pushGetPrefs",
      "id": "A3646A8D40C5B7319416179833809496",
      "attributes": {
        "preferences": [
          {
            "preferenceId": "appointment_reminders",
            "preferenceName": "Appointment reminders",
            "value": true
          },
          {
            "preferenceName": "New secure messages",
            "preferenceId": "secure_message_alerts",
            "value": true
          }
        ]
      }
    }
  }
}
